[
    {
        "id": "1",
        "name": "Verona",
        "size": "20 cm",
        "price": "9.50"
    },
    {
        "id": "2",
        "name": "Verona",
        "size": "27 cm",
        "price": "16.00"
    },
    {
        "id": "3",
        "name": "Verona",
        "size": "40 cm",
        "price": "25.90"
    },
    {
        "id": "4",
        "name": "Verona",
        "size": "60 cm",
        "price": "45.40"
    },
    {
        "id": "5",
        "name": "Ostra Kura",
        "size": "20 cm",
        "price": "12.50"
    },
    {
        "id": "6",
        "name": "Ostra Kura",
        "size": "27 cm",
        "price": "20.90"
    },
    {
        "id": "7",
        "name": "Ostra Kura",
        "size": "40 cm",
        "price": "31.90"
    },
    {
        "id": "8",
        "name": "Ostra Kura",
        "size": "60 cm",
        "price": "62.00"
    },
    {
        "id": "9",
        "name": "Amore",
        "size": "20 cm",
        "price": "12.00"
    },
    {
        "id": "10",
        "name": "Amore",
        "size": "27 cm",
        "price": "18.00"
    },
    {
        "id": "11",
        "name": "Amore",
        "size": "40 cm",
        "price": "29.90"
    },
    {
        "id": "12",
        "name": "Amore",
        "size": "60 cm",
        "price": "59.80"
    },
    {
        "id": "13",
        "name": "Feta",
        "size": "20 cm",
        "price": "11.50"
    },
    {
        "id": "14",
        "name": "Feta",
        "size": "27 cm",
        "price": "18.10"
    },
    {
        "id": "15",
        "name": "Feta",
        "size": "40 cm",
        "price": "32.50"
    },
    {
        "id": "16",
        "name": "Feta",
        "size": "60 cm",
        "price": "62.40"
    },
    {
        "id": "17",
        "name": "Venezia",
        "size": "20 cm",
        "price": "10.00"
    },
    {
        "id": "18",
        "name": "Venezia",
        "size": "27 cm",
        "price": "17.50"
    },
    {
        "id": "19",
        "name": "Venezia",
        "size": "40 cm",
        "price": "31.50"
    },
    {
        "id": "20",
        "name": "Venezia",
        "size": "60 cm",
        "price": "57.50"
    },
    {
        "id": "21",
        "name": "Chorizo",
        "size": "20 cm",
        "price": "11.50"
    },
    {
        "id": "22",
        "name": "Chorizo",
        "size": "27 cm",
        "price": "18.70"
    },
    {
        "id": "23",
        "name": "Chorizo",
        "size": "40 cm",
        "price": "33.60"
    },
    {
        "id": "24",
        "name": "Chorizo",
        "size": "60 cm",
        "price": "59.50"
    },
    {
        "id": "25",
        "name": "Hawajska",
        "size": "20 cm",
        "price": "9.50"
    },
    {
        "id": "26",
        "name": "Hawajska",
        "size": "27 cm",
        "price": "16.50"
    },
    {
        "id": "27",
        "name": "Hawajska",
        "size": "40 cm",
        "price": "29.10"
    },
    {
        "id": "28",
        "name": "Hawajska",
        "size": "60 cm",
        "price": "58.20"
    },
    {
        "id": "29",
        "name": "Vege",
        "size": "20 cm",
        "price": "11.50"
    },
    {
        "id": "30",
        "name": "Vege",
        "size": "27 cm",
        "price": "17.50"
    },
    {
        "id": "31",
        "name": "Vege",
        "size": "40 cm",
        "price": "30.20"
    },
    {
        "id": "32",
        "name": "Vege",
        "size": "60 cm",
        "price": "59.50"
    },
    {
        "id": "33",
        "name": "La Bamba",
        "size": "20 cm",
        "price": "12.50"
    },
    {
        "id": "34",
        "name": "La Bamba",
        "size": "27 cm",
        "price": "20.90"
    },
    {
        "id": "35",
        "name": "La Bamba",
        "size": "40 cm",
        "price": "36.60"
    },
    {
        "id": "36",
        "name": "La Bamba",
        "size": "60 cm",
        "price": "69.90"
    },
    {
        "id": "37",
        "name": "Mexicana",
        "size": "20 cm",
        "price": "11.00"
    },
    {
        "id": "38",
        "name": "Mexicana",
        "size": "27 cm",
        "price": "17.00"
    },
    {
        "id": "39",
        "name": "Mexicana",
        "size": "40 cm",
        "price": "28.90"
    },
    {
        "id": "40",
        "name": "Mexicana",
        "size": "60 cm",
        "price": "55.80"
    },
    {
        "id": "41",
        "name": "Coca-Cola",
        "size": "0.5 l",
        "price": "7.00"
    },
    {
        "id": "42",
        "name": "Coca-Cola",
        "size": "0.85 l",
        "price": "9.00"
    },
    {
        "id": "43",
        "name": "Fanta",
        "size": "0.5 l",
        "price": "7.00"
    },
    {
        "id": "44",
        "name": "Sprite",
        "size": "0.5 l",
        "price": "7.00"
    },
    {
        "id": "45",
        "name": "Red Bull",
        "size": "0.25 l",
        "price": "9.00"
    },
    {
        "id": "46",
        "name": "Piwo Żywiec",
        "size": "0.5 l",
        "price": "8.50"
    },
    {
        "id": "47",
        "name": "Radler Warka 0%",
        "size": "0.5 l",
        "price": "6.40"
    }
]